platymatch/__init__.py
platymatch/_dock_widget.py
platymatch/_tests/__init__.py
platymatch/_tests/test_dock_widget.py
platymatch/_tests/test_estimate_transform.py
platymatch/_tests/test_ss_log.py
platymatch/_tests/test_utils.py
platymatch/detect_nuclei/__init__.py
platymatch/detect_nuclei/ss_log.py
platymatch/estimate_transform/__init__.py
platymatch/estimate_transform/apply_transform.py
platymatch/estimate_transform/find_transform.py
platymatch/estimate_transform/perform_icp.py
platymatch/estimate_transform/shape_context.py
platymatch/utils/__init__.py
platymatch/utils/utils.py
PlatyMatch-0.0.3.dist-info/LICENSE
PlatyMatch-0.0.3.dist-info/METADATA
PlatyMatch-0.0.3.dist-info/WHEEL
PlatyMatch-0.0.3.dist-info/entry_points.txt
PlatyMatch-0.0.3.dist-info/top_level.txt
PlatyMatch-0.0.3.dist-info/RECORD
