Metadata-Version: 2.1
Name: PlatyMatch
Version: 0.0.3
Summary: PlatyMatch allows registration of volumetric images of embryos by establishing correspondences between cells
Home-page: https://github.com/juglab/PlatyMatch
Author: Manan Lalit
Author-email: lalit@mpi-cbg.de
License: BSD-3
Platform: UNKNOWN
Classifier: Development Status :: 4 - Beta
Classifier: Intended Audience :: Developers
Classifier: Framework :: napari
Classifier: Topic :: Software Development :: Testing
Classifier: Programming Language :: Python
Classifier: Programming Language :: Python :: 3
Classifier: Programming Language :: Python :: 3.7
Classifier: Programming Language :: Python :: 3.8
Classifier: Programming Language :: Python :: 3.9
Classifier: Operating System :: OS Independent
Classifier: License :: OSI Approved :: BSD License
Requires-Python: >=3.6
License-File: LICENSE
Requires-Dist: napari-plugin-engine (>=0.1.4)
Requires-Dist: numpy
Requires-Dist: scikit-image
Requires-Dist: scikit-learn
Requires-Dist: tqdm
Requires-Dist: simpleitk
Requires-Dist: napari[all]
Requires-Dist: pandas
Requires-Dist: pytest
